kolortext/__init__.py
kolortext/bg.py
kolortext/control.py
kolortext/fg.py
kolortext/helper.py
kolortext/reset.py
kolortext/style.py
kolortext-0.0.1.dist-info/METADATA
kolortext-0.0.1.dist-info/WHEEL
kolortext-0.0.1.dist-info/licenses/LICENSE.txt
kolortext-0.0.1.dist-info/RECORD
