Metadata-Version: 2.1
Name: kolortext
Version: 0.0.1
Summary: Print colored text in python and perform color conversions
Project-URL: Homepage, https://github.com/Samuel9360639/kolortext
Project-URL: Issues, https://github.com/Samuel9360639/kolortext/issues
Project-URL: Contribute, https://github.com/Samuel9360639/kolortext/pulls
Author-email: Samuel <samuel.9360639@gmail.com>
License: MIT
License-File: LICENSE.txt
Keywords: ANSI,Color,Text
Classifier: Development Status :: 5 - Production/Stable
Classifier: License :: OSI Approved :: MIT License
Classifier: Operating System :: OS Independent
Classifier: Programming Language :: Python :: 3
Requires-Python: >=3.7
